aininja/__init__.py
aininja/main.py
aininja-0.1.3.dist-info/METADATA
aininja-0.1.3.dist-info/WHEEL
aininja-0.1.3.dist-info/entry_points.txt
aininja-0.1.3.dist-info/RECORD
