Metadata-Version: 2.4
Name: aininja
Version: 0.1.3
Summary: AI Powered Assistant For Developers
Author: Rajat Ratewal
Requires-Python: >=3.9
Provides-Extra: dev
Requires-Dist: build; extra == 'dev'
Requires-Dist: hatchling; extra == 'dev'
Requires-Dist: twine; extra == 'dev'
